{
 "charts": [],
 "content": "[{\"id\":\"pGDIKaB3sp\",\"type\":\"header\",\"data\":{\"text\":\"<span class=\\\"h4\\\">ICL Finance</span>\",\"col\":12}},{\"id\":\"J7vPhqvR5k\",\"type\":\"paragraph\",\"data\":{\"text\":\"<b>IntelliSOFT Consulting Limited</b>\",\"col\":12}},{\"id\":\"Q6nv3ukJ_0\",\"type\":\"card\",\"data\":{\"card_name\":\"Timesheet\",\"col\":4}},{\"id\":\"Bu53a4s5pU\",\"type\":\"header\",\"data\":{\"text\":\"<span class=\\\"h4\\\"><b>Shortcuts</b></span>\",\"col\":12}},{\"id\":\"bg707X16ZX\",\"type\":\"card\",\"data\":{\"card_name\":\"Payroll Shortcuts\",\"col\":4}},{\"id\":\"ig1g1wBMZt\",\"type\":\"card\",\"data\":{\"card_name\":\"Projects\",\"col\":4}},{\"id\":\"TBV1hg88lO\",\"type\":\"header\",\"data\":{\"text\":\"<span class=\\\"h4\\\"><b>Reports</b></span>\",\"col\":12}}]",
 "creation": "2024-09-16 09:22:40.305577",
 "custom_blocks": [],
 "docstatus": 0,
 "doctype": "Workspace",
 "for_user": "",
 "hide_custom": 0,
 "idx": 0,
 "indicator_color": "green",
 "is_hidden": 0,
 "label": "ICL Finance",
 "links": [
  {
   "hidden": 0,
   "is_query_report": 0,
   "label": "Timesheet",
   "link_count": 2,
   "link_type": "DocType",
   "onboard": 0,
   "type": "Card Break"
  },
  {
   "hidden": 0,
   "is_query_report": 0,
   "label": "Timesheet Submission",
   "link_count": 0,
   "link_to": "Timesheet Submission",
   "link_type": "DocType",
   "onboard": 0,
   "type": "Link"
  },
  {
   "hidden": 0,
   "is_query_report": 0,
   "label": "Timesheet",
   "link_count": 0,
   "link_to": "Timesheet",
   "link_type": "DocType",
   "onboard": 0,
   "type": "Link"
  },
  {
   "hidden": 0,
   "is_query_report": 0,
   "label": "Projects",
   "link_count": 5,
   "link_type": "DocType",
   "onboard": 0,
   "type": "Card Break"
  },
  {
   "hidden": 0,
   "is_query_report": 0,
   "label": "Task",
   "link_count": 0,
   "link_to": "Task",
   "link_type": "DocType",
   "onboard": 0,
   "type": "Link"
  },
  {
   "hidden": 0,
   "is_query_report": 0,
   "label": "Task Type",
   "link_count": 0,
   "link_to": "Task Type",
   "link_type": "DocType",
   "onboard": 0,
   "type": "Link"
  },
  {
   "hidden": 0,
   "is_query_report": 0,
   "label": "Timesheet",
   "link_count": 0,
   "link_to": "Timesheet",
   "link_type": "DocType",
   "onboard": 0,
   "type": "Link"
  },
  {
   "hidden": 0,
   "is_query_report": 0,
   "label": "Activity Type",
   "link_count": 0,
   "link_to": "Activity Type",
   "link_type": "DocType",
   "onboard": 0,
   "type": "Link"
  },
  {
   "hidden": 0,
   "is_query_report": 0,
   "label": "Activity Cost",
   "link_count": 0,
   "link_to": "Activity Cost",
   "link_type": "DocType",
   "onboard": 0,
   "type": "Link"
  },
  {
   "hidden": 0,
   "is_query_report": 0,
   "label": "Payroll Shortcuts",
   "link_count": 4,
   "link_type": "DocType",
   "onboard": 0,
   "type": "Card Break"
  },
  {
   "hidden": 0,
   "is_query_report": 0,
   "label": "Salary Component",
   "link_count": 0,
   "link_to": "Salary Component",
   "link_type": "DocType",
   "onboard": 0,
   "type": "Link"
  },
  {
   "hidden": 0,
   "is_query_report": 0,
   "label": "Salary Structure",
   "link_count": 0,
   "link_to": "Salary Structure",
   "link_type": "DocType",
   "onboard": 0,
   "type": "Link"
  },
  {
   "hidden": 0,
   "is_query_report": 0,
   "label": "Salary Slip",
   "link_count": 0,
   "link_to": "Salary Slip",
   "link_type": "DocType",
   "onboard": 0,
   "type": "Link"
  },
  {
   "hidden": 0,
   "is_query_report": 0,
   "label": "Salary Structure Assignment",
   "link_count": 0,
   "link_to": "Salary Structure Assignment",
   "link_type": "DocType",
   "onboard": 0,
   "type": "Link"
  }
 ],
 "modified": "2024-09-16 16:04:35.206497",
 "modified_by": "Administrator",
 "module": "ICL Corporate Services",
 "name": "ICL Finance",
 "number_cards": [],
 "owner": "Administrator",
 "parent_page": "",
 "public": 1,
 "quick_lists": [],
 "roles": [],
 "sequence_id": 43.0,
 "shortcuts": [],
 "title": "ICL Finance"
}