[
 {
  "allow_guest": 0,
  "api_method": null,
  "cron_format": null,
  "disabled": 1,
  "docstatus": 0,
  "doctype": "Server Script",
  "doctype_event": "Before Submit",
  "enable_rate_limit": 0,
  "event_frequency": "All",
  "modified": "2026-02-18 08:48:24.148527",
  "module": "ICL Corporate Services",
  "name": "Quiz Scoring Script",
  "rate_limit_count": 5,
  "rate_limit_seconds": 86400,
  "reference_doctype": "Quiz Submission",
  "script": "def split_values(value):\n    if not value:\n        return []\n\n    text = (value or '').replace('|||', '\\n').replace(',', '\\n')\n    return [part.strip() for part in text.splitlines() if part.strip()]\n\n\ndef normalize(value):\n    return (value or '').strip().lower()\n\n\ndef get_defined_options(question):\n    if (question.answer_options or '').strip():\n        return [value.strip() for value in question.answer_options.splitlines() if value.strip()]\n\n    return [value.strip() for value in [question.option_a, question.option_b, question.option_c, question.option_d] if value]\n\n\ndef get_option_lookup(question):\n    options = get_defined_options(question)\n    lookup = {}\n\n    for index, option in enumerate(options):\n        normalized_option = normalize(option)\n        lookup[normalized_option] = option\n        if index < 26:\n            lookup[chr(ord('a') + index)] = option\n\n    return lookup\n\n\ndef resolve_answers(question, raw_value):\n    lookup = get_option_lookup(question)\n    resolved = []\n\n    for answer in split_values(raw_value):\n        resolved.append(lookup.get(normalize(answer), answer.strip()))\n\n    return resolved\n\n\ndef get_correct_answers(question):\n    return resolve_answers(question, question.correct_answer)\n\n\ndef is_correct_response(question, selected_answer):\n    question_type = question.question_type or 'Single Select'\n    correct_answers = get_correct_answers(question)\n\n    if question_type == 'Open Ended':\n        return None\n\n    if question_type == 'Multi Select':\n        selected_values = {normalize(value) for value in resolve_answers(question, selected_answer)}\n        correct_values = {normalize(value) for value in correct_answers}\n        return bool(correct_values) and selected_values == correct_values\n\n    normalized_selected = normalize(resolve_answers(question, selected_answer)[0] if split_values(selected_answer) else '')\n    return normalized_selected in {normalize(value) for value in correct_answers}\n\n\ndef before_submit(doc, method):\n    correct = 0\n    total = len(doc.answers)\n    gradable_total = 0\n    has_pending_review = False\n\n    for row in doc.answers:\n        question = frappe.get_doc('Quiz Question', row.question)\n        question_type = question.question_type or 'Single Select'\n        correct_answers = get_correct_answers(question)\n        normalized_selected_answers = resolve_answers(question, row.selected_answer)\n        is_correct = is_correct_response(question, row.selected_answer)\n\n        row.question_text = question.question\n        row.question_type = question_type\n        row.selected_answer = '\\n'.join(normalized_selected_answers)\n        row.correct_answer = '\\n'.join(correct_answers)\n\n        if is_correct is None:\n            row.is_correct = 0\n            has_pending_review = True\n        else:\n            row.is_correct = 1 if is_correct else 0\n            gradable_total += 1\n            if row.is_correct:\n                correct += 1\n\n    doc.total_questions = total\n    doc.correct_answers = correct\n    doc.score_ = round((correct / gradable_total) * 100, 2) if gradable_total > 0 else 0\n\n    quiz = frappe.get_doc('Quiz', doc.quiz)\n    passing_score = quiz.passing_score_ or 70\n\n    if has_pending_review:\n        doc.passed = 0\n        doc.result = 'Pending Review'\n    elif doc.score_ >= passing_score:\n        doc.passed = 1\n        doc.result = 'Pass'\n    else:\n        doc.passed = 0\n        doc.result = 'Fail'",
  "script_type": "DocType Event"
 },
 {
  "allow_guest": 0,
  "api_method": null,
  "cron_format": null,
  "disabled": 0,
  "docstatus": 0,
  "doctype": "Server Script",
  "doctype_event": "Before Insert",
  "enable_rate_limit": 0,
  "event_frequency": "All",
  "modified": "2026-03-17 12:28:41.644450",
  "module": "ICL Corporate Services",
  "name": "Quiz Question Naming Series",
  "rate_limit_count": 5,
  "rate_limit_seconds": 86400,
  "reference_doctype": "Quiz Question",
  "script": "name = (doc.question or \"\")[:50].strip()\n\nif frappe.db.exists(\"Quiz Question\", name):\n    name = name + \"-\" + frappe.utils.random_string(4)\n\ndoc.id = name",
  "script_type": "DocType Event"
 },
 {
  "allow_guest": 0,
  "api_method": null,
  "cron_format": null,
  "disabled": 0,
  "docstatus": 0,
  "doctype": "Server Script",
  "doctype_event": "Before Insert",
  "enable_rate_limit": 0,
  "event_frequency": "All",
  "modified": "2026-03-17 12:38:53.458229",
  "module": "ICL Corporate Services",
  "name": "Quiz Naming Series",
  "rate_limit_count": 5,
  "rate_limit_seconds": 86400,
  "reference_doctype": "Quiz",
  "script": "name = (doc.quiz_title or \"\")[:50].strip()\n\nif frappe.db.exists(\"Quiz\", name):\n    name = name + \"-\" + frappe.utils.random_string(4)\n\ndoc.id = name",
  "script_type": "DocType Event"
 }
]