[
 {
  "docstatus": 0,
  "doctype": "Workflow Action Master",
  "modified": "2026-04-10 13:52:23.549797",
  "name": "Save",
  "workflow_action_name": "Save"
 },
 {
  "docstatus": 0,
  "doctype": "Workflow Action Master",
  "modified": "2026-04-10 13:52:23.557442",
  "name": "Review",
  "workflow_action_name": "Review"
 },
 {
  "docstatus": 0,
  "doctype": "Workflow Action Master",
  "modified": "2026-04-10 13:52:23.561998",
  "name": "Submit to Finance",
  "workflow_action_name": "Submit to Finance"
 },
 {
  "docstatus": 0,
  "doctype": "Workflow Action Master",
  "modified": "2026-04-10 13:52:23.568904",
  "name": "Needs Clarification",
  "workflow_action_name": "Needs Clarification"
 },
 {
  "docstatus": 0,
  "doctype": "Workflow Action Master",
  "modified": "2026-04-10 13:52:23.574689",
  "name": "Submit to HR",
  "workflow_action_name": "Submit to HR"
 },
 {
  "docstatus": 0,
  "doctype": "Workflow Action Master",
  "modified": "2026-04-10 13:52:23.579762",
  "name": "submit",
  "workflow_action_name": "submit"
 },
 {
  "docstatus": 0,
  "doctype": "Workflow Action Master",
  "modified": "2026-04-10 13:52:23.584346",
  "name": "NO/GO",
  "workflow_action_name": "NO/GO"
 },
 {
  "docstatus": 0,
  "doctype": "Workflow Action Master",
  "modified": "2026-04-10 13:52:23.589088",
  "name": "GO",
  "workflow_action_name": "GO"
 },
 {
  "docstatus": 0,
  "doctype": "Workflow Action Master",
  "modified": "2026-04-10 13:52:23.593637",
  "name": "Submit To supervisor",
  "workflow_action_name": "Submit To supervisor"
 },
 {
  "docstatus": 0,
  "doctype": "Workflow Action Master",
  "modified": "2026-04-10 13:52:23.598159",
  "name": "Approve",
  "workflow_action_name": "Approve"
 },
 {
  "docstatus": 0,
  "doctype": "Workflow Action Master",
  "modified": "2026-04-10 13:52:23.602858",
  "name": "Reject",
  "workflow_action_name": "Reject"
 },
 {
  "docstatus": 0,
  "doctype": "Workflow Action Master",
  "modified": "2026-04-10 13:52:23.607774",
  "name": "Submit to Project Manager",
  "workflow_action_name": "Submit to Project Manager"
 }
]