{
 "actions": [],
 "allow_rename": 1,
 "creation": "2024-10-30 08:25:01.213725",
 "doctype": "DocType",
 "editable_grid": 1,
 "engine": "InnoDB",
 "field_order": [
  "budget_line",
  "sub_budget_line",
  "unit_loe_type",
  "unit_loe",
  "rate",
  "cost"
 ],
 "fields": [
  {
   "fieldname": "budget_line",
   "fieldtype": "Link",
   "in_list_view": 1,
   "label": "Budget Line",
   "options": "Payment Entry Budget Line",
   "reqd": 1
  },
  {
   "fieldname": "sub_budget_line",
   "fieldtype": "Data",
   "in_list_view": 1,
   "label": "Sub Budget Line"
  },
  {
   "fieldname": "unit_loe",
   "fieldtype": "Data",
   "in_list_view": 1,
   "label": "Unit LOE"
  },
  {
   "fieldname": "rate",
   "fieldtype": "Data",
   "in_list_view": 1,
   "label": "Rate"
  },
  {
   "fieldname": "cost",
   "fieldtype": "Data",
   "in_list_view": 1,
   "label": "Cost",
   "read_only": 1
  },
  {
   "fieldname": "unit_loe_type",
   "fieldtype": "Data",
   "in_list_view": 1,
   "label": "Unit LOE Type"
  }
 ],
 "index_web_pages_for_search": 1,
 "istable": 1,
 "links": [],
 "modified": "2024-11-25 11:19:23.823365",
 "modified_by": "Administrator",
 "module": "ICL Corporate Services",
 "name": "Budget Line Template",
 "owner": "Administrator",
 "permissions": [],
 "sort_field": "modified",
 "sort_order": "DESC",
 "states": []
}